[
  {"id":"em-fc-1","front":"Formule de l'énergie cinétique ?","back":"$E_c = \\frac{1}{2} \\times m \\times v^2$ (J, kg, m/s).","difficulty":1},
  {"id":"em-fc-2","front":"Formule de l'énergie potentielle ?","back":"$E_p = m \\times g \\times h$ (J, kg, N/kg, m).","difficulty":1},
  {"id":"em-fc-3","front":"Formule de l'énergie mécanique ?","back":"$E_m = E_c + E_p$.","difficulty":1},
  {"id":"em-fc-4","front":"Si la vitesse double, que devient $E_c$ ?","back":"$E_c$ est multipliée par 4 (la vitesse est au carré).","difficulty":2},
  {"id":"em-fc-5","front":"Que vaut $g$ sur Terre ?","back":"$g \\approx 9{,}8\\,N/kg$ (parfois arrondi à 10).","difficulty":1},
  {"id":"em-fc-6","front":"Conservation de l'énergie mécanique : quand ?","back":"Sans frottement, $E_m$ reste constante. $E_p$ et $E_c$ s'échangent.","difficulty":2},
  {"id":"em-fc-7","front":"Comment convertir km/h en m/s ?","back":"Diviser par 3,6. Ex : $72\\,km/h = 20\\,m/s$.","difficulty":1},
  {"id":"em-fc-8","front":"Au sommet d'une chute libre (v=0), quelle énergie ?","back":"$E_c = 0$. Toute l'énergie est potentielle : $E_m = E_p$.","difficulty":2}
]
